<?xml version="1.0" encoding="utf-8" ?>
<dwsync>
<file name="IMG_8729_JPG.gif" server="carmenbook.freehostia.com/carmenbook.freehostia.com/" local="129141467612250000" remote="129141198000000000" />
<file name="IMG_8702_JPG.gif" server="carmenbook.freehostia.com/carmenbook.freehostia.com/" local="129141467595290000" remote="129141198000000000" />
<file name="IMG_8701_JPG.gif" server="carmenbook.freehostia.com/carmenbook.freehostia.com/" local="129141467588240000" remote="129141198000000000" />
<file name="IMG_8697_JPG.gif" server="carmenbook.freehostia.com/carmenbook.freehostia.com/" local="129141467581350000" remote="129141198000000000" />
<file name="IMG_8696_JPG.gif" server="carmenbook.freehostia.com/carmenbook.freehostia.com/" local="129141467573530000" remote="129141198000000000" />
<file name="IMG_8688_JPG.gif" server="carmenbook.freehostia.com/carmenbook.freehostia.com/" local="129141467557150000" remote="129141198000000000" />
<file name="IMG_8664_JPG.gif" server="carmenbook.freehostia.com/carmenbook.freehostia.com/" local="129141467541600000" remote="129141198000000000" />
<file name="IMG_8659_JPG.gif" server="carmenbook.freehostia.com/carmenbook.freehostia.com/" local="129141467521040000" remote="129141198000000000" />
<file name="IMG_8656_JPG.gif" server="carmenbook.freehostia.com/carmenbook.freehostia.com/" local="129141467513930000" remote="129141198000000000" />
<file name="IMG_8651_JPG.gif" server="carmenbook.freehostia.com/carmenbook.freehostia.com/" local="129141467506960000" remote="129141198000000000" />
<file name="IMG_8638_JPG.gif" server="carmenbook.freehostia.com/carmenbook.freehostia.com/" local="129141467500180000" remote="129141198000000000" />
<file name="IMG_8605_JPG.gif" server="carmenbook.freehostia.com/carmenbook.freehostia.com/" local="129141467493040000" remote="129141198000000000" />
<file name="IMG_8587_JPG.gif" server="carmenbook.freehostia.com/carmenbook.freehostia.com/" local="129141467485970000" remote="129141198000000000" />
</dwsync>