<?xml version="1.0" encoding="utf-8" ?>
<dwsync>
<file name="IMG_7686_JPG.htm" server="carmenbook.freehostia.com/carmenbook.freehostia.com/" local="129141578475510000" remote="129141298200000000" />
<file name="IMG_7680_JPG.htm" server="carmenbook.freehostia.com/carmenbook.freehostia.com/" local="129141578475350000" remote="129141298200000000" />
<file name="IMG_7644_JPG.htm" server="carmenbook.freehostia.com/carmenbook.freehostia.com/" local="129141578475200000" remote="129141298200000000" />
<file name="IMG_7637_JPG.htm" server="carmenbook.freehostia.com/carmenbook.freehostia.com/" local="129141578475040000" remote="129141298200000000" />
<file name="IMG_7630_JPG.htm" server="carmenbook.freehostia.com/carmenbook.freehostia.com/" local="129141578474880000" remote="129141298200000000" />
<file name="IMG_7582_JPG.htm" server="carmenbook.freehostia.com/carmenbook.freehostia.com/" local="129141578474720000" remote="129141298200000000" />
<file name="IMG_7579_JPG.htm" server="carmenbook.freehostia.com/carmenbook.freehostia.com/" local="129141578474570000" remote="129141298200000000" />
<file name="IMG_7553_JPG.htm" server="carmenbook.freehostia.com/carmenbook.freehostia.com/" local="129141578474130000" remote="129141298200000000" />
<file name="IMG_7541_JPG.htm" server="carmenbook.freehostia.com/carmenbook.freehostia.com/" local="129141578473650000" remote="129141298200000000" />
<file name="IMG_7519_JPG.htm" server="carmenbook.freehostia.com/carmenbook.freehostia.com/" local="129141578473440000" remote="129141298200000000" />
<file name="IMG_7506_JPG.htm" server="carmenbook.freehostia.com/carmenbook.freehostia.com/" local="129141578473300000" remote="129141298200000000" />
<file name="IMG_7502_JPG.htm" server="carmenbook.freehostia.com/carmenbook.freehostia.com/" local="129141578473160000" remote="129141298200000000" />
<file name="IMG_7499_JPG.htm" server="carmenbook.freehostia.com/carmenbook.freehostia.com/" local="129141578473010000" remote="129141298200000000" />
<file name="IMG_7495_JPG.htm" server="carmenbook.freehostia.com/carmenbook.freehostia.com/" local="129141578472920000" remote="129141298200000000" />
</dwsync>