<?xml version="1.0" encoding="utf-8" ?>
<dwsync>
<file name="BAJ010305.JPG" server="carmenbook.freehostia.com/carmenbook.freehostia.com/" local="125962866740000000" remote="129160569600000000" />
<file name="BAJ010313.JPG" server="carmenbook.freehostia.com/carmenbook.freehostia.com/" local="129059526529226000" remote="129160569600000000" />
<file name="BAJ010349.JPG" server="carmenbook.freehostia.com/carmenbook.freehostia.com/" local="125962866820000000" remote="129160569600000000" />
<file name="BAJ010987.JPG" server="carmenbook.freehostia.com/carmenbook.freehostia.com/" local="125337385200000000" remote="129160569600000000" />
<file name="086.JPG" server="carmenbook.freehostia.com/carmenbook.freehostia.com/" local="125679472980000000" remote="129160569600000000" />
<file name="BAJ010253.JPG" server="carmenbook.freehostia.com/carmenbook.freehostia.com/" local="125962866660000000" remote="129160569600000000" />
<file name="BAJ010960.JPG" server="carmenbook.freehostia.com/carmenbook.freehostia.com/" local="125337385120000000" remote="129160569600000000" />
<file name="BAJ010992.JPG" server="carmenbook.freehostia.com/carmenbook.freehostia.com/" local="125337385220000000" remote="129160569600000000" />
<file name="BAJ010281.JPG" server="carmenbook.freehostia.com/carmenbook.freehostia.com/" local="125962866700000000" remote="129160569600000000" />
<file name="BAJ010281-1.jpg" server="carmenbook.freehostia.com/carmenbook.freehostia.com/" local="129065310601330000" remote="129160569600000000" />
<file name="BAJ010005.jpg" server="carmenbook.freehostia.com/carmenbook.freehostia.com/" local="129116274665397000" remote="129160569600000000" />
<file name="bac010030.gif" server="carmenbook.freehostia.com/carmenbook.freehostia.com/" local="125934167860000000" remote="129279241200000000" />
<file name="002.GIF" server="carmenbook.freehostia.com/carmenbook.freehostia.com/" local="129308052217073647" remote="129328595400000000" />
<file name="002.jpg" server="carmenbook.freehostia.com/carmenbook.freehostia.com/" local="129308051211943647" remote="129307782000000000" />
</dwsync>